alberta_framework/__init__.py
alberta_framework/py.typed
alberta_framework/core/__init__.py
alberta_framework/core/learners.py
alberta_framework/core/normalizers.py
alberta_framework/core/optimizers.py
alberta_framework/core/types.py
alberta_framework/streams/__init__.py
alberta_framework/streams/base.py
alberta_framework/streams/gymnasium.py
alberta_framework/streams/synthetic.py
alberta_framework/utils/__init__.py
alberta_framework/utils/experiments.py
alberta_framework/utils/export.py
alberta_framework/utils/metrics.py
alberta_framework/utils/statistics.py
alberta_framework/utils/timing.py
alberta_framework/utils/visualization.py
alberta_framework-0.1.0.dist-info/METADATA
alberta_framework-0.1.0.dist-info/WHEEL
alberta_framework-0.1.0.dist-info/licenses/LICENSE
alberta_framework-0.1.0.dist-info/RECORD
