Metadata-Version: 2.4
Name: alberta-framework
Version: 0.1.0
Summary: Implementation of the Alberta Plan for AI Research - continual learning with meta-learned step-sizes
Project-URL: Homepage, https://github.com/j-klawson/alberta-framework
Project-URL: Repository, https://github.com/j-klawson/alberta-framework
Project-URL: Documentation, https://j-klawson.github.io/alberta-framework
Project-URL: Issues, https://github.com/j-klawson/alberta-framework/issues
Author-email: "J. Klawson" <j-klawson@users.noreply.github.com>
License-Expression: Apache-2.0
License-File: LICENSE
Keywords: continual-learning,jax,machine-learning,meta-learning,reinforcement-learning
Classifier: Development Status :: 3 - Alpha
Classifier: Intended Audience :: Science/Research
Classifier: License :: OSI Approved :: Apache Software License
Classifier: Programming Language :: Python :: 3
Classifier: Programming Language :: Python :: 3.13
Classifier: Topic :: Scientific/Engineering :: Artificial Intelligence
Requires-Python: >=3.13
Requires-Dist: jax>=0.4
Requires-Dist: jaxlib>=0.4
Requires-Dist: joblib>=1.3
Requires-Dist: matplotlib>=3.8
Requires-Dist: numpy>=2.0
Requires-Dist: scipy>=1.11
Requires-Dist: tqdm>=4.66
Provides-Extra: dev
Requires-Dist: mypy; extra == 'dev'
Requires-Dist: pytest-cov; extra == 'dev'
Requires-Dist: pytest>=8.0; extra == 'dev'
Requires-Dist: ruff; extra == 'dev'
Provides-Extra: docs
Requires-Dist: mkdocs-gen-files>=0.5; extra == 'docs'
Requires-Dist: mkdocs-literate-nav>=0.6; extra == 'docs'
Requires-Dist: mkdocs-material>=9.5; extra == 'docs'
Requires-Dist: mkdocs-section-index>=0.3; extra == 'docs'
Requires-Dist: mkdocs>=1.6; extra == 'docs'
Requires-Dist: mkdocstrings[python]>=0.24; extra == 'docs'
Provides-Extra: gpu
Requires-Dist: jax[cuda12]>=0.4; extra == 'gpu'
Provides-Extra: gymnasium
Requires-Dist: gymnasium>=0.29.0; extra == 'gymnasium'
